fetchyt/__init__.py
fetchyt/api.py
fetchyt/cli.py
fetchyt/config.py
fetchyt/downloader.py
fetchyt/models.py
fetchyt/static/index.html
fetchyt/static/css/style.css
fetchyt/static/js/app.js
fetchyt-0.1.1.dist-info/METADATA
fetchyt-0.1.1.dist-info/WHEEL
fetchyt-0.1.1.dist-info/entry_points.txt
fetchyt-0.1.1.dist-info/top_level.txt
fetchyt-0.1.1.dist-info/RECORD
