Metadata-Version: 2.4
Name: fetchyt
Version: 0.1.1
Summary: Download MP3s from YouTube playlists with FastAPI backend and web interface
Author-email: Krishnakanth Allika <silica-mop-outlast@duck.com>
License-Expression: CC-BY-NC-SA-4.0
Project-URL: Homepage, https://go.allika.eu.org/fetchyt
Project-URL: Repository, https://gitlab.com/allikapub/fetchyt
Project-URL: Issues, https://gitlab.com/allikapub/fetchyt/-/issues
Keywords: youtube,download,mp3,playlist,fastapi,cli
Classifier: Development Status :: 3 - Alpha
Classifier: Intended Audience :: End Users/Desktop
Classifier: Programming Language :: Python :: 3
Classifier: Programming Language :: Python :: 3.12
Classifier: Programming Language :: Python :: 3.13
Requires-Python: >=3.12
Requires-Dist: aiofiles>=25.1.0
Requires-Dist: fastapi>=0.128.0
Requires-Dist: pydantic>=2.12.5
Requires-Dist: python-multipart>=0.0.21
Requires-Dist: uvicorn>=0.40.0
Requires-Dist: yt-dlp>=2025.12.8
